odoo/addons/sale_order_report_hide_tax/README.rst
odoo/addons/sale_order_report_hide_tax/__init__.py
odoo/addons/sale_order_report_hide_tax/__manifest__.py
odoo/addons/sale_order_report_hide_tax/i18n/it.po
odoo/addons/sale_order_report_hide_tax/i18n/sale_order_report_hide_tax.pot
odoo/addons/sale_order_report_hide_tax/models/__init__.py
odoo/addons/sale_order_report_hide_tax/models/sale_order.py
odoo/addons/sale_order_report_hide_tax/readme/CONTEXT.md
odoo/addons/sale_order_report_hide_tax/readme/CONTRIBUTORS.md
odoo/addons/sale_order_report_hide_tax/readme/DESCRIPTION.md
odoo/addons/sale_order_report_hide_tax/readme/USAGE.md
odoo/addons/sale_order_report_hide_tax/reports/sale_order_report_template.xml
odoo/addons/sale_order_report_hide_tax/static/description/icon.png
odoo/addons/sale_order_report_hide_tax/static/description/index.html
odoo_addon_sale_order_report_hide_tax-16.0.1.0.1.2.dist-info/METADATA
odoo_addon_sale_order_report_hide_tax-16.0.1.0.1.2.dist-info/WHEEL
odoo_addon_sale_order_report_hide_tax-16.0.1.0.1.2.dist-info/top_level.txt
odoo_addon_sale_order_report_hide_tax-16.0.1.0.1.2.dist-info/RECORD
