Metadata-Version: 2.1
Name: odoo-addon-sale_order_report_hide_tax
Version: 16.0.1.0.1.2
Summary: Hide taxes column when they don't add value
Home-page: https://github.com/OCA/sale-reporting
Author: Moduon, Odoo Community Association (OCA)
Author-email: support@odoo-community.org
License: LGPL-3
Classifier: Programming Language :: Python
Classifier: Framework :: Odoo
Classifier: Framework :: Odoo :: 16.0
Classifier: License :: OSI Approved :: GNU Lesser General Public License v3 (LGPLv3)
Classifier: Development Status :: 3 - Alpha
Requires-Python: >=3.10
Requires-Dist: odoo<16.1dev,>=16.0a
